{"cameraMode":{"drawMode":0,"name":"Shaded","section":"Shading Mode"},"sceneLighting":true,"audioPlay":false,"sceneViewState":{"m_AlwaysRefresh":false,"showFog":true,"showSkybox":true,"showFlares":true,"showImageEffects":true,"showParticleSystems":true,"showVisualEffectGraphs":true,"m_FxEnabled":true},"in2DMode":false,"pivot":{"x":-800.598388671875,"y":-37.45169448852539,"z":1507.7357177734375},"rotation":{"x":0.2592998147010803,"y":-0.06352907419204712,"z":0.017147859558463098,"w":0.9638352990150452},"size":91.19245910644531,"orthographic":false}