{"cameraMode":{"drawMode":0,"name":"Shaded","section":"Shading Mode"},"sceneLighting":true,"audioPlay":false,"sceneViewState":{"m_AlwaysRefresh":false,"showFog":true,"showSkybox":true,"showFlares":true,"showImageEffects":true,"showParticleSystems":true,"showVisualEffectGraphs":true,"m_FxEnabled":true},"in2DMode":false,"pivot":{"x":186.6852569580078,"y":70.77416229248047,"z":34.31229782104492},"rotation":{"x":-0.09313403815031052,"y":-0.7694775462150574,"z":0.11535812169313431,"w":-0.621238112449646},"size":12.461819648742676,"orthographic":false}